{
  "resourceType" : "CodeSystem",
  "id" : "92a035ce-143c-4d1a-9a4e-fb2b63790588-131",
  "url" : "http://hl7.org/fhir/comparison/CodeSystem/92a035ce-143c-4d1a-9a4e-fb2b63790588-131",
  "name" : "UnionSharingApprovalPoliciesAndSharingApprovalPolicies",
  "title" : "Union of Sharing Approval Policies And Sharing Approval Policies",
  "status" : "active",
  "date" : "2025-03-06T12:22:51+00:00",
  "jurisdiction" : [{
    "coding" : [{
      "system" : "urn:iso:std:iso:3166",
      "code" : "DK",
      "display" : "Denmark"
    }]
  }],
  "concept" : [{
    "code" : "manual",
    "display" : "Manual",
    "definition" : "Document sharing must be approved manually",
    "designation" : [{
      "language" : "da",
      "value" : "Deling af dokument skal godkendes manuelt"
    }]
  },
  {
    "code" : "automatic",
    "display" : "Automatic",
    "definition" : "Document sharing is approved automatically",
    "designation" : [{
      "language" : "da",
      "value" : "Deling af dokument bliver godkendt automatisk"
    }]
  }]
}