{
  "resourceType" : "CodeSystem",
  "id" : "cb28daf9-f8fe-4e02-87d4-13d28f777d12-383",
  "url" : "http://hl7.org/fhir/comparison/CodeSystem/cb28daf9-f8fe-4e02-87d4-13d28f777d12-383",
  "name" : "UnionDanish-SNOMED-CT-ExtensionAndDanish-SNOMED-CT-Extension",
  "title" : "Union of Danish SNOMED CT Extension And Danish SNOMED CT Extension",
  "status" : "active",
  "date" : "2025-08-12T12:56:04+00:00",
  "jurisdiction" : [{
    "coding" : [{
      "system" : "urn:iso:std:iso:3166",
      "code" : "DK",
      "display" : "Denmark"
    }]
  }],
  "concept" : [{
    "code" : "557671000005101",
    "display" : "Osteopathy clinic",
    "definition" : "Osteopathy clinic",
    "designation" : [{
      "language" : "da",
      "value" : "osteopatiklinik"
    }]
  }]
}