{
  "packages" : [
    {
      "path" : "fhir/package-list.json",
      "package-id" : "dk.ehealth.sundhed.fhir.ig.core",
      "title" : "FUT Infrastructure",
      "canonical" : "http://ehealth.sundhed.dk/fhir",
      "category" : "Core",
      "ci-build" : "https://build.fhir.org/ig/fut-infrastructure/implementation-guide/",
      "version-count" : 3,
      "latest" : {
        "version" : "3.3.0",
        "date" : "2024-11-05",
        "path" : "http://ehealth.sundhed.dk/fhir/3.3.0"
      },
      "milestone" : {
        "version" : "3.3.0",
        "date" : "2024-11-05",
        "path" : "http://ehealth.sundhed.dk/fhir/3.3.0"
      }
    }
  ]
}
