{
  "resourceType" : "ValueSet",
  "id" : "a3dd2ad3-418a-4ff6-927c-55d26d04b8ad-1239",
  "url" : "http://hl7.org/fhir/comparison/ValueSet/a3dd2ad3-418a-4ff6-927c-55d26d04b8ad-1239",
  "name" : "IntersectionRelationshipTypesAndRelationshipTypes",
  "title" : "Intersection of null And null",
  "status" : "active",
  "date" : "2025-04-29T12:18:48+00:00",
  "jurisdiction" : [{
    "coding" : [{
      "system" : "urn:iso:std:iso:3166",
      "code" : "DK",
      "display" : "Denmark"
    }]
  }],
  "compose" : {
    "include" : [{
      "concept" : [{
        "code" : "FAMMEMB",
        "display" : "family member"
      },
      {
        "code" : "SIB",
        "display" : "sibling"
      },
      {
        "code" : "DOMPART",
        "display" : "domestic partner"
      },
      {
        "code" : "ROOM",
        "display" : "Roommate"
      },
      {
        "code" : "U",
        "display" : "Unknown"
      },
      {
        "code" : "NBOR",
        "display" : "neighbor"
      },
      {
        "code" : "CHLDINLAW",
        "display" : "child-in-law"
      },
      {
        "code" : "GRNDCHILD",
        "display" : "grandchild"
      },
      {
        "code" : "PRN",
        "display" : "parent"
      },
      {
        "code" : "O",
        "display" : "Other"
      },
      {
        "code" : "CHILD",
        "display" : "child"
      },
      {
        "code" : "SPS",
        "display" : "spouse"
      }]
    }]
  }
}