{
  "resourceType" : "ValueSet",
  "id" : "3705dcd7-d5ce-4904-9e91-7aba5649cbf7-1326",
  "url" : "http://hl7.org/fhir/comparison/ValueSet/3705dcd7-d5ce-4904-9e91-7aba5649cbf7-1326",
  "name" : "IntersectionReferenceRangeTypeAndReferenceRangeType",
  "title" : "Intersection of Reference Range Type And Reference Range Type",
  "status" : "active",
  "date" : "2025-10-23T13:17:41+00:00",
  "jurisdiction" : [{
    "coding" : [{
      "system" : "urn:iso:std:iso:3166",
      "code" : "DK",
      "display" : "Denmark"
    }]
  }],
  "compose" : {
    "include" : [{
      
    },
    {
      "valueSet" : ["http://ehealth.sundhed.dk/vs/observation-codes"]
    },
    {
      "concept" : [{
        "code" : "RAL",
        "display" : "Terapeutiske grænseværdier for RØD alarm"
      },
      {
        "code" : "GAL",
        "display" : "Terapeutiske grænseværdier for GUL alarm"
      }]
    },
    {
      
    }]
  }
}