{
  "resourceType" : "CodeSystem",
  "id" : "1b6dba59-02e9-4f2c-84f7-bde2b0a6a412-144",
  "url" : "http://hl7.org/fhir/comparison/CodeSystem/1b6dba59-02e9-4f2c-84f7-bde2b0a6a412-144",
  "name" : "IntersectionmediaUsageModeAndmediaUsageMode",
  "title" : "Intersection of Media usage mode And Media usage mode",
  "status" : "active",
  "date" : "2025-08-11T07:12:05+00:00",
  "jurisdiction" : [{
    "coding" : [{
      "system" : "urn:iso:std:iso:3166",
      "code" : "DK",
      "display" : "Denmark"
    }]
  }],
  "concept" : [{
    "code" : "raw",
    "display" : "Raw",
    "definition" : "Raw",
    "designation" : [{
      "language" : "da",
      "value" : "Original"
    }]
  },
  {
    "code" : "overlay",
    "display" : "Overlay",
    "definition" : "Overlay",
    "designation" : [{
      "language" : "da",
      "value" : "Overlay"
    }]
  },
  {
    "code" : "metadata",
    "display" : "Metadata",
    "definition" : "Metadata",
    "designation" : [{
      "language" : "da",
      "value" : "Metadata"
    }]
  }]
}