{
  "resourceType" : "ValueSet",
  "id" : "4fecf118-5c3e-4ab7-94dd-c773f20cc4c5-1274",
  "url" : "http://hl7.org/fhir/comparison/ValueSet/4fecf118-5c3e-4ab7-94dd-c773f20cc4c5-1274",
  "name" : "UnionQuestionnaireTypesAndQuestionnaireTypes",
  "title" : "Union of Questionnaire Types And Questionnaire Types",
  "status" : "active",
  "date" : "2026-03-03T10:27:52+00:00",
  "jurisdiction" : [{
    "coding" : [{
      "system" : "urn:iso:std:iso:3166",
      "code" : "DK",
      "display" : "Denmark"
    }]
  }],
  "compose" : {
    "include" : [{
      
    },
    {
      "concept" : [{
        "code" : "273586006",
        "display" : "Master Questionnaire (DK)"
      }]
    }]
  }
}