{
  "resourceType" : "CodeSystem",
  "id" : "3705dcd7-d5ce-4904-9e91-7aba5649cbf7-200",
  "url" : "http://hl7.org/fhir/comparison/CodeSystem/3705dcd7-d5ce-4904-9e91-7aba5649cbf7-200",
  "name" : "UnioneHealthProgramAndeHealthProgram",
  "title" : "Union of eHealth Program And eHealth Program",
  "status" : "active",
  "date" : "2025-10-23T13:16:58+00:00",
  "jurisdiction" : [{
    "coding" : [{
      "system" : "urn:iso:std:iso:3166",
      "code" : "DK",
      "display" : "Denmark"
    }]
  }],
  "concept" : [{
    "code" : "kpro",
    "display" : "Kommunal PRO",
    "definition" : "Kommunal patientrapporterede oplysninger"
  },
  {
    "code" : "telma",
    "display" : "Telma",
    "definition" : "Telemedicinsk monitoreringsapplikation"
  },
  {
    "code" : "telma-support-team",
    "display" : "Telma Supportteam",
    "definition" : "Supportteam for Telemedicinsk monitoreringsapplikation"
  }]
}