{
  "resourceType" : "CodeSystem",
  "id" : "70abb295-48d3-4068-a5e7-c2e7d334d0da-131",
  "url" : "http://hl7.org/fhir/comparison/CodeSystem/70abb295-48d3-4068-a5e7-c2e7d334d0da-131",
  "name" : "UnionLibraryTypeAndLibraryType",
  "title" : "Union of Library Type And Library Type",
  "status" : "active",
  "date" : "2025-08-08T06:50:04+00:00",
  "jurisdiction" : [{
    "coding" : [{
      "system" : "urn:iso:std:iso:3166",
      "code" : "DK",
      "display" : "Denmark"
    }]
  }],
  "concept" : [{
    "code" : "automated-processing",
    "display" : "Automated Processing",
    "definition" : "The resource defines an evaluation context for automated processing",
    "designation" : [{
      "language" : "da",
      "value" : "Ressourcen definerer en regel og dennes kontekst til brug i automatisk processering"
    }]
  }]
}